aica_api/__init__.py
aica_api/client.py
aica_api/errors.py
aica_api/sio_client.py
aica_api/sdk/sdk/__init__.py
aica_api/sdk/sdk/client.py
aica_api/sdk/sdk/errors.py
aica_api/sdk/sdk/types.py
aica_api/sdk/sdk/api/__init__.py
aica_api/sdk/sdk/api/api/__init__.py
aica_api/sdk/sdk/api/api/get_api_schema_yaml.py
aica_api/sdk/sdk/api/api/get_api_version.py
aica_api/sdk/sdk/api/api/get_documentation_website.py
aica_api/sdk/sdk/api/applications/__init__.py
aica_api/sdk/sdk/api/applications/create_application.py
aica_api/sdk/sdk/api/applications/create_new_application_version.py
aica_api/sdk/sdk/api/applications/delete_application.py
aica_api/sdk/sdk/api/applications/delete_application_from_cloud.py
aica_api/sdk/sdk/api/applications/delete_application_version.py
aica_api/sdk/sdk/api/applications/delete_cloud_application.py
aica_api/sdk/sdk/api/applications/download_cloud_application.py
aica_api/sdk/sdk/api/applications/get_application.py
aica_api/sdk/sdk/api/applications/get_application_version.py
aica_api/sdk/sdk/api/applications/get_applications.py
aica_api/sdk/sdk/api/applications/update_application.py
aica_api/sdk/sdk/api/applications/update_application_version.py
aica_api/sdk/sdk/api/applications/upload_application_to_cloud.py
aica_api/sdk/sdk/api/auth/__init__.py
aica_api/sdk/sdk/api/auth/login.py
aica_api/sdk/sdk/api/auth/logout.py
aica_api/sdk/sdk/api/cloud/__init__.py
aica_api/sdk/sdk/api/cloud/get_cloud_status.py
aica_api/sdk/sdk/api/cloud/start_cloud_auth.py
aica_api/sdk/sdk/api/cloud/sync_cloud_apps.py
aica_api/sdk/sdk/api/custom_components/__init__.py
aica_api/sdk/sdk/api/custom_components/convert_custom_component_from_snippet_to_source.py
aica_api/sdk/sdk/api/custom_components/create_custom_component.py
aica_api/sdk/sdk/api/custom_components/create_new_custom_component_version.py
aica_api/sdk/sdk/api/custom_components/delete_custom_component.py
aica_api/sdk/sdk/api/custom_components/delete_custom_component_version.py
aica_api-4.0.2.dist-info/METADATA
aica_api-4.0.2.dist-info/WHEEL
aica_api-4.0.2.dist-info/licenses/LICENSE
aica_api-4.0.2.dist-info/RECORD
