Metadata-Version: 2.4
Name: aica_api
Version: 4.0.2
Summary: A client utility for the AICA API
Project-URL: Homepage, https://github.com/aica-technology/api
Project-URL: Bug Tracker, https://github.com/aica-technology/api/issues
Author-email: Enrico Eberhard <enrico@aica.tech>
License-File: LICENSE
Classifier: License :: OSI Approved :: MIT License
Classifier: Operating System :: OS Independent
Classifier: Programming Language :: Python :: 3
Requires-Python: >=3.9
Requires-Dist: attrs>=22.2.0
Requires-Dist: deprecation~=2.1.0
Requires-Dist: httpx<0.29.0,>=0.23.0
Requires-Dist: python-dateutil~=2.8.0
Requires-Dist: python-socketio[client]~=5.11.0
Requires-Dist: semver~=3.0.2
